{
  "animateLoading": true,
  "borderRadius": "{{appsmith.theme.borderRadius.appBorderRadius}}",
  "bottomRow": 25,
  "displayName": "Text",
  "dynamicBindingPathList": [
    {
      "key": "truncateButtonColor"
    },
    {
      "key": "fontFamily"
    },
    {
      "key": "borderRadius"
    },
    {
      "key": "text"
    }
  ],
  "dynamicHeight": "FIXED",
  "dynamicPropertyPathList": [],
  "dynamicTriggerPathList": [],
  "fontFamily": "{{appsmith.theme.fontFamily.appFont}}",
  "fontSize": "0.875rem",
  "fontStyle": "BOLD",
  "hideCard": false,
  "iconSVG": "/static/media/icon.97c59b523e6f70ba6f40a10fc2c7c5b5.svg",
  "isDeprecated": false,
  "isLoading": false,
  "isVisible": true,
  "key": "k0zn3vv2el",
  "leftColumn": 39,
  "maxDynamicHeight": 9000,
  "minDynamicHeight": 4,
  "minWidth": 450,
  "mobileBottomRow": 13,
  "mobileLeftColumn": 0,
  "mobileRightColumn": 16,
  "mobileTopRow": 9,
  "overflow": "NONE",
  "parentColumnSpace": 6.767578125,
  "parentId": "lvya69kw4u",
  "parentRowSpace": 10,
  "renderMode": "CANVAS",
  "responsiveBehavior": "fill",
  "rightColumn": 62,
  "searchTags": [
    "typography",
    "paragraph",
    "label"
  ],
  "shouldTruncate": false,
  "text": "{{Utils.myCurrency(\nNumber(Partial_profit.text.replace(/[^0-9.-]+/g,\"\")) - Number(Mb_comm.text.replace(/[^0-9.-]+/g,\"\")) - Factory_costs.value\n)}}",
  "textAlign": "RIGHT",
  "textColor": "",
  "topRow": 21,
  "truncateButtonColor": "{{appsmith.theme.colors.primaryColor}}",
  "type": "TEXT_WIDGET",
  "version": 1,
  "widgetId": "ke1cjg5k91",
  "widgetName": "Profit"
}