{
  "gitSyncId": "63936c0b4b95806da2da5de7_63b2004b0bc0a80b3001759e",
  "id": "Login_sign_up",
  "pluginId": "restapi-plugin",
  "pluginType": "API",
  "unpublishedAction": {
    "actionConfiguration": {
      "body": "{\n  \"email\": \"{{InputEmailCopy.text}}\",\n  \"password\": \"{{InputPasswordCopy.text}}\"\n}",
      "encodeParamsToggle": true,
      "formData": {
        "apiContentType": "application/json"
      },
      "headers": [
        {
          "key": "content-type",
          "value": "application/json"
        }
      ],
      "httpMethod": "POST",
      "paginationType": "NONE",
      "path": "/auth/v1/signup",
      "queryParameters": [],
      "timeoutInMillisecond": 10000
    },
    "confirmBeforeExecute": false,
    "datasource": {
      "id": "Auth",
      "isAutoGenerated": false,
      "name": "Auth",
      "pluginId": "restapi-plugin"
    },
    "dynamicBindingPathList": [
      {
        "key": "body"
      }
    ],
    "name": "sign_up",
    "pageId": "Login",
    "runBehaviour": "MANUAL",
    "userSetOnLoad": false
  }
}