{
  "animateLoading": true,
  "backgroundColor": "#FFFFFF",
  "borderColor": "#E0DEDE",
  "borderRadius": "{{appsmith.theme.borderRadius.appBorderRadius}}",
  "borderWidth": "1",
  "bottomRow": 76,
  "boxShadow": "{{appsmith.theme.boxShadow.appBoxShadow}}",
  "children": [
    {
      "bottomRow": 680,
      "canExtend": false,
      "containerStyle": "none",
      "detachFromLayout": true,
      "displayName": "Canvas",
      "dynamicBindingPathList": [],
      "flexLayers": [],
      "hideCard": true,
      "isDeprecated": false,
      "isLoading": false,
      "isVisible": true,
      "key": "ex9nxn3gwh",
      "leftColumn": 0,
      "minHeight": 100,
      "minWidth": 450,
      "mobileBottomRow": 100,
      "mobileLeftColumn": 0,
      "mobileRightColumn": 197.65625,
      "mobileTopRow": 0,
      "parentColumnSpace": 1,
      "parentId": "olhnb4k696",
      "parentRowSpace": 1,
      "renderMode": "CANVAS",
      "responsiveBehavior": "fill",
      "rightColumn": 197.65625,
      "topRow": 0,
      "type": "CANVAS_WIDGET",
      "version": 1,
      "widgetId": "yk14q2fw2h",
      "widgetName": "Canvas14"
    }
  ],
  "containerStyle": "card",
  "displayName": "Container",
  "dynamicBindingPathList": [
    {
      "key": "borderRadius"
    },
    {
      "key": "boxShadow"
    }
  ],
  "dynamicHeight": "AUTO_HEIGHT",
  "flexVerticalAlignment": "start",
  "hideCard": false,
  "iconSVG": "/static/media/icon.c47c069fe28eb6d2d27f0fffdc053074.svg",
  "isCanvas": true,
  "isDeprecated": false,
  "isLoading": false,
  "isVisible": true,
  "key": "nlwj8ms9pi",
  "leftColumn": 0,
  "maxDynamicHeight": 9000,
  "minDynamicHeight": 10,
  "minWidth": 450,
  "mobileBottomRow": 18,
  "mobileLeftColumn": 0,
  "mobileRightColumn": 10,
  "mobileTopRow": 8,
  "originalBottomRow": 76,
  "originalTopRow": 8,
  "parentColumnSpace": 19.765625,
  "parentId": "qd74yy4u3t",
  "parentRowSpace": 10,
  "renderMode": "CANVAS",
  "responsiveBehavior": "fill",
  "rightColumn": 11,
  "searchTags": [
    "div",
    "parent",
    "group"
  ],
  "shouldScrollContents": true,
  "topRow": 8,
  "type": "CONTAINER_WIDGET",
  "version": 1,
  "widgetId": "olhnb4k696",
  "widgetName": "Container2"
}