{
  "gitSyncId": "63c3151532584b547fffe91b_63c7b07308759c023fd98987",
  "id": "Day by Day_get_off_category",
  "pluginId": "restapi-plugin",
  "pluginType": "API",
  "unpublishedAction": {
    "actionConfiguration": {
      "encodeParamsToggle": true,
      "headers": [
        {
          "key": "Authorization",
          "value": "Bearer {{appsmith.store.access_token}}"
        }
      ],
      "httpMethod": "GET",
      "paginationType": "NONE",
      "path": "/rest/v1/offer_category",
      "queryParameters": [
        {
          "key": "select",
          "value": "*"
        }
      ],
      "timeoutInMillisecond": 10000
    },
    "confirmBeforeExecute": false,
    "datasource": {
      "id": "Auth",
      "isAutoGenerated": false,
      "name": "Auth",
      "pluginId": "restapi-plugin"
    },
    "dynamicBindingPathList": [
      {
        "key": "headers[0].value"
      }
    ],
    "name": "get_off_category",
    "pageId": "Day by Day",
    "runBehaviour": "MANUAL",
    "userSetOnLoad": true
  }
}