{
  "borderRadius": "0px",
  "bottomRow": 4,
  "boxShadow": "none",
  "dynamicBindingPathList": [
    {
      "key": "fontFamily"
    }
  ],
  "dynamicHeight": "FIXED",
  "dynamicPropertyPathList": [],
  "dynamicTriggerPathList": [],
  "fontFamily": "{{appsmith.theme.fontFamily.appFont}}",
  "fontSize": "1rem",
  "fontStyle": "",
  "isLoading": false,
  "isVisible": "true",
  "labelTextSize": "0.875rem",
  "leftColumn": 0,
  "maxDynamicHeight": 9000,
  "minDynamicHeight": 4,
  "overflow": "NONE",
  "parentColumnSpace": 3.0322265625,
  "parentId": "uku4q4r2tg",
  "parentRowSpace": 10,
  "rightColumn": 64,
  "text": "Profit",
  "textAlign": "CENTER",
  "textColor": "#231F20",
  "topRow": 0,
  "type": "TEXT_WIDGET",
  "version": 1,
  "widgetId": "dgh23m3j60",
  "widgetName": "Text16Copy1CopyCopy1"
}