{
  "animateLoading": true,
  "borderRadius": "{{appsmith.theme.borderRadius.appBorderRadius}}",
  "bottomRow": 5,
  "boxShadow": "none",
  "buttonColor": "#fde047",
  "buttonVariant": "PRIMARY",
  "disabledWhenInvalid": false,
  "dynamicBindingPathList": [
    {
      "key": "borderRadius"
    }
  ],
  "dynamicTriggerPathList": [
    {
      "key": "onClick"
    }
  ],
  "isDefaultClickDisabled": true,
  "isDisabled": false,
  "isLoading": false,
  "isVisible": true,
  "key": "et6rdntgnf",
  "leftColumn": 26,
  "minWidth": 120,
  "mobileBottomRow": 5,
  "mobileLeftColumn": 23,
  "mobileRightColumn": 39,
  "mobileTopRow": 1,
  "needsErrorInfo": false,
  "onClick": "{{showModal(Modal1.name);}}",
  "parentColumnSpace": 18.375,
  "parentId": "kuzt0s9qm0",
  "parentRowSpace": 10,
  "placement": "CENTER",
  "recaptchaType": "V3",
  "renderMode": "CANVAS",
  "resetFormOnClick": false,
  "responsiveBehavior": "hug",
  "rightColumn": 39,
  "text": "Offers Categories",
  "topRow": 1,
  "type": "BUTTON_WIDGET",
  "version": 1,
  "widgetId": "mtaantbyh3",
  "widgetName": "Button1"
}