{
    "resetFormOnClick": false,
    "boxShadow": "none",
    "widgetName": "Button1",
    "onClick": "{{closeModal('Modal1')}}",
    "buttonColor": "{{appsmith.theme.colors.primaryColor}}",
    "displayName": "Button",
    "iconSVG": "/static/media/icon.cca026338f1c8eb6df8ba03d084c2fca.svg",
    "searchTags": [
        "click",
        "submit"
    ],
    "topRow": 19,
    "bottomRow": 23,
    "type": "BUTTON_WIDGET",
    "hideCard": false,
    "animateLoading": true,
    "leftColumn": 0,
    "dynamicBindingPathList": [
        {"key": "buttonColor"},
        {"key": "borderRadius"}
    ],
    "text": "Close",
    "isDisabled": false,
    "key": "1m3vb7ugl0",
    "isDeprecated": false,
    "rightColumn": 31,
    "isDefaultClickDisabled": true,
    "widgetId": "axuxlxh18y",
    "buttonStyle": "PRIMARY",
    "minWidth": 120,
    "isVisible": true,
    "recaptchaType": "V3",
    "version": 1,
    "parentId": "nk5ita9iuy",
    "renderMode": "CANVAS",
    "isLoading": false,
    "responsiveBehavior": "hug",
    "originalTopRow": 17,
    "disabledWhenInvalid": false,
    "borderRadius": "{{appsmith.theme.borderRadius.appBorderRadius}}",
    "originalBottomRow": 21,
    "buttonVariant": "SECONDARY",
    "placement": "CENTER"
}